mikeio1d/__init__.py
mikeio1d/custom_exceptions.py
mikeio1d/dotnet.py
mikeio1d/mikepath.py
mikeio1d/query.py
mikeio1d/res1d.py
mikeio1d/top_level.py
mikeio1d/various.py
mikeio1d/xns11.py
mikeio1d/bin/DHI.Mike1D.Application.runtimeconfig.json
mikeio1d/bin/__init__.py
mikeio1d/cross_sections/__init__.py
mikeio1d/cross_sections/cross_section.py
mikeio1d/cross_sections/cross_section_collection.py
mikeio1d/cross_sections/cross_section_factory.py
mikeio1d/cross_sections/enums.py
mikeio1d/cross_sections/marker.py
mikeio1d/filter/__init__.py
mikeio1d/filter/name_filter.py
mikeio1d/filter/quantity_filter.py
mikeio1d/filter/result_filter.py
mikeio1d/filter/step_every_filter.py
mikeio1d/filter/time_filter.py
mikeio1d/geometry/__init__.py
mikeio1d/geometry/catchment_geometry.py
mikeio1d/geometry/cross_section_geometry.py
mikeio1d/geometry/node_point.py
mikeio1d/geometry/protocols.py
mikeio1d/geometry/reach_geometry.py
mikeio1d/geometry/reach_point.py
mikeio1d/geometry/geopandas/__init__.py
mikeio1d/geometry/geopandas/geopandas_catchments_converter.py
mikeio1d/geometry/geopandas/geopandas_converter.py
mikeio1d/geometry/geopandas/geopandas_nodes_converter.py
mikeio1d/geometry/geopandas/geopandas_reaches_converter.py
mikeio1d/geometry/geopandas/geopandas_reaches_converter_segmented.py
mikeio1d/mikenet/__init__.py
mikeio1d/mikenet/library_loader.py
mikeio1d/mikenet/library_loaders.py
mikeio1d/pandas_extension/__init__.py
mikeio1d/pandas_extension/mikeio1d_accessor.py
mikeio1d/pandas_extension/result_frame_aggregator.py
mikeio1d/pandas_extension/result_reaches_helpers.py
mikeio1d/pandas_extension/transposed_groupby.py
mikeio1d/pandas_extension/various.py
mikeio1d/quantities/__init__.py
mikeio1d/quantities/timeseries_id.py
mikeio1d/quantities/derived/__init__.py
mikeio1d/quantities/derived/derived_quantity.py
mikeio1d/quantities/derived/derived_quantity_example.py
mikeio1d/quantities/derived/derived_quantity_manager.py
mikeio1d/quantities/derived/default_quantities/__init__.py
mikeio1d-1.1.1.dist-info/METADATA
mikeio1d-1.1.1.dist-info/WHEEL
mikeio1d-1.1.1.dist-info/licenses/LICENSE
mikeio1d-1.1.1.dist-info/RECORD
