Metadata-Version: 2.4
Name: mikeio1d
Version: 1.1.1
Summary: A package that uses the DHI MIKE1D .NET libraries to read res1d and xns11 files.
Project-URL: Homepage, https://github.com/DHI/mikeio1d
Project-URL: Bug Tracker, https://github.com/DHI/mikeio1d/issues
Author-email: Gediminas Kirsanskas <geki@dhigroup.com>
License: MIT License
License-File: LICENSE
Classifier: Development Status :: 4 - Beta
Classifier: Intended Audience :: Science/Research
Classifier: License :: OSI Approved :: MIT License
Classifier: Operating System :: Microsoft :: Windows
Classifier: Operating System :: POSIX :: Linux
Classifier: Programming Language :: Python
Classifier: Programming Language :: Python :: 3
Classifier: Programming Language :: Python :: 3.9
Classifier: Programming Language :: Python :: 3.10
Classifier: Programming Language :: Python :: 3.11
Classifier: Programming Language :: Python :: 3.12
Classifier: Programming Language :: Python :: 3.13
Classifier: Topic :: Scientific/Engineering
Requires-Python: >=3.9
Requires-Dist: matplotlib
Requires-Dist: mikecore; platform_system == 'Linux'
Requires-Dist: numpy
Requires-Dist: pandas>=2.1.0
Requires-Dist: pythonnet>=3.0.0
Provides-Extra: all
Requires-Dist: geopandas; extra == 'all'
Requires-Dist: matplotlib; extra == 'all'
Provides-Extra: dev
Requires-Dist: folium; extra == 'dev'
Requires-Dist: geopandas; extra == 'dev'
Requires-Dist: hatch; extra == 'dev'
Requires-Dist: jupyterlab; extra == 'dev'
Requires-Dist: mapclassify; extra == 'dev'
Requires-Dist: matplotlib; extra == 'dev'
Requires-Dist: pytest; extra == 'dev'
Requires-Dist: pytest-cov; extra == 'dev'
Requires-Dist: ruff; extra == 'dev'
Provides-Extra: docs
Requires-Dist: quarto-cli==1.6.37; extra == 'docs'
Requires-Dist: quartodoc==0.9.1; extra == 'docs'
Provides-Extra: notebooks
Requires-Dist: folium; extra == 'notebooks'
Requires-Dist: geopandas; extra == 'notebooks'
Requires-Dist: ipykernel; extra == 'notebooks'
Requires-Dist: mapclassify; extra == 'notebooks'
Requires-Dist: matplotlib; extra == 'notebooks'
Requires-Dist: nbconvert; extra == 'notebooks'
Requires-Dist: nbformat; extra == 'notebooks'
Provides-Extra: test
Requires-Dist: ipykernel; extra == 'test'
Requires-Dist: matplotlib; extra == 'test'
Requires-Dist: nbconvert; extra == 'test'
Requires-Dist: nbformat; extra == 'test'
Requires-Dist: pyarrow; extra == 'test'
Requires-Dist: pytest; extra == 'test'
Requires-Dist: pytest-cov; extra == 'test'
